pytest_sort/__init__.py
pytest_sort/config.py
pytest_sort/core.py
pytest_sort/database.py
pytest_sort/diffcov.py
pytest_sort/plugin.py
pytest_sort-1.3.2.dist-info/licenses/LICENSE
pytest_sort-1.3.2.dist-info/METADATA
pytest_sort-1.3.2.dist-info/WHEEL
pytest_sort-1.3.2.dist-info/entry_points.txt
pytest_sort-1.3.2.dist-info/top_level.txt
pytest_sort-1.3.2.dist-info/RECORD
