Metadata-Version: 2.4
Name: pytest-sort
Version: 1.3.2
Summary: Tools for sorting test cases
Author-email: WiredNerd <pbuschmail-pytestsort@yahoo.com>
Maintainer-email: WiredNerd <pbuschmail-pytestsort@yahoo.com>
License: MIT License
Project-URL: Documentation, https://pytest-sort.readthedocs.io/
Project-URL: Homepage, https://github.com/WiredNerd/pytest-sort
Project-URL: Issue Tracker, https://github.com/WiredNerd/pytest-sort/issues
Keywords: test,pytest,order,pytest-order,sort,random,pytest-random,pytest-random-order,randomly,pytest-randomly
Classifier: Programming Language :: Python :: 3
Classifier: License :: OSI Approved :: MIT License
Classifier: Operating System :: OS Independent
Classifier: Framework :: Pytest
Requires-Python: >=3.8
License-File: LICENSE
Requires-Dist: pytest>=7.4.0
Requires-Dist: whatthepatch>=1.0.5
Requires-Dist: coverage>=7.3.1
Dynamic: license-file
